luke/__init__.py
luke/format.py
luke/generators.py
luke/main.py
luke/openapi.py
luke/schemas.py
luke/server.py
py_luke-0.0.3.dist-info/METADATA
py_luke-0.0.3.dist-info/WHEEL
py_luke-0.0.3.dist-info/entry_points.txt
py_luke-0.0.3.dist-info/licenses/LICENSE
py_luke-0.0.3.dist-info/RECORD
