Metadata-Version: 2.1
Name: py-luke
Version: 0.0.3
Summary: Mock server for OpenAPI documentation
Project-URL: Homepage, https://github.com/magiskboy/luke
Project-URL: Documentation, https://github.com/magiskboy/luke#features
Project-URL: Issues, https://github.com/magiskboy/luke/issues/
Project-URL: Source, https://github.com/magiskboy/luke
Author-email: Nguyen Khac Thanh <nguyenkhacthanh244@gmail.com>
License-Expression: MIT
License-File: LICENSE
Keywords: bundle openapi,jsonschema,mock server,openapi,validate openapi
Classifier: Development Status :: 3 - Alpha
Classifier: Environment :: Web Environment
Classifier: Framework :: AnyIO
Classifier: Intended Audience :: Developers
Classifier: License :: OSI Approved :: MIT License
Classifier: Operating System :: OS Independent
Classifier: Programming Language :: Python :: 3
Classifier: Programming Language :: Python :: 3.7
Classifier: Programming Language :: Python :: 3.8
Classifier: Programming Language :: Python :: 3.9
Classifier: Programming Language :: Python :: 3.10
Classifier: Programming Language :: Python :: 3.11
Classifier: Topic :: Internet :: WWW/HTTP
Requires-Python: >=3.7
Requires-Dist: faker
Requires-Dist: httpx
Requires-Dist: jsonschema
Requires-Dist: py-xeger
Requires-Dist: pyyaml
Requires-Dist: starlette
Requires-Dist: typer
Requires-Dist: uvicorn
Provides-Extra: dev
Requires-Dist: mypy; extra == 'dev'
Requires-Dist: pre-commit; extra == 'dev'
Requires-Dist: pytest-cov==4.0.0; extra == 'dev'
Requires-Dist: pytest==7.3.1; extra == 'dev'
Requires-Dist: ruff; extra == 'dev'
Requires-Dist: types-pyyaml; extra == 'dev'
